url_crawler/__init__.py
url_crawler/url_crawler.py
url_crawler-1.0.0.dist-info/LICENSE
url_crawler-1.0.0.dist-info/METADATA
url_crawler-1.0.0.dist-info/WHEEL
url_crawler-1.0.0.dist-info/top_level.txt
url_crawler-1.0.0.dist-info/RECORD
