Metadata-Version: 2.1
Name: url-crawler
Version: 1.0.0
Summary: A Python library to crawl the details of a URL.
Home-page: https://github.com/iampukar/url_crawler
Author: Pukar Acharya
License: UNKNOWN
Project-URL: Bug Tracker, https://github.com/iampukar/url_crawler/issues
Platform: UNKNOWN
Classifier: Programming Language :: Python :: 3
Classifier: License :: OSI Approved :: MIT License
Requires-Python: >=3.9.7
License-File: LICENSE
